[
{"category":"Hobi & Hiburan","difficulty":"easy","question":"Sebutkan hobi yang sering dilakukan di rumah","answers":[{"answer":"menonton","score":30},{"answer":"main game","score":25},{"answer":"membaca","score":20},{"answer":"tidur","score":15},{"answer":"memasak","score":10}]},
{"category":"Hobi & Hiburan","difficulty":"easy","question":"Sebutkan kegiatan saat waktu luang","answers":[{"answer":"main game","score":30},{"answer":"nonton","score":25},{"answer":"tidur","score":20},{"answer":"jalan-jalan","score":15},{"answer":"mendengarkan musik","score":10}]},
{"category":"Hobi & Hiburan","difficulty":"easy","question":"Sebutkan jenis game yang populer","answers":[{"answer":"moba","score":30},{"answer":"fps","score":25},{"answer":"rpg","score":20},{"answer":"battle royale","score":15},{"answer":"racing","score":10}]},
{"category":"Hobi & Hiburan","difficulty":"easy","question":"Sebutkan kegiatan saat liburan","answers":[{"answer":"jalan-jalan","score":30},{"answer":"tidur","score":25},{"answer":"main game","score":20},{"answer":"nonton","score":15},{"answer":"berenang","score":10}]},
{"category":"Hobi & Hiburan","difficulty":"easy","question":"Sebutkan jenis musik yang populer","answers":[{"answer":"pop","score":30},{"answer":"rock","score":25},{"answer":"dangdut","score":20},{"answer":"hip hop","score":15},{"answer":"jazz","score":10}]},
{"category":"Hobi & Hiburan","difficulty":"easy","question":"Sebutkan aktivitas saat bosan","answers":[{"answer":"main hp","score":30},{"answer":"tidur","score":25},{"answer":"nonton","score":20},{"answer":"main game","score":15},{"answer":"makan","score":10}]},
{"category":"Hobi & Hiburan","difficulty":"easy","question":"Sebutkan kegiatan di akhir pekan","answers":[{"answer":"jalan-jalan","score":30},{"answer":"nonton","score":25},{"answer":"main game","score":20},{"answer":"tidur","score":15},{"answer":"nongkrong","score":10}]},
{"category":"Hobi & Hiburan","difficulty":"easy","question":"Sebutkan kegiatan yang dilakukan bersama teman","answers":[{"answer":"nongkrong","score":30},{"answer":"main game","score":25},{"answer":"nonton","score":20},{"answer":"jalan-jalan","score":15},{"answer":"makan","score":10}]},
{"category":"Hobi & Hiburan","difficulty":"easy","question":"Sebutkan platform untuk menonton","answers":[{"answer":"youtube","score":35},{"answer":"netflix","score":25},{"answer":"tv","score":20},{"answer":"disney+","score":10},{"answer":"bioskop","score":10}]},
{"category":"Hobi & Hiburan","difficulty":"easy","question":"Sebutkan aktivitas yang bikin senang","answers":[{"answer":"main game","score":30},{"answer":"jalan-jalan","score":25},{"answer":"makan","score":20},{"answer":"nonton","score":15},{"answer":"tidur","score":10}]},
{"category":"Hobi & Hiburan","difficulty":"easy","question":"Sebutkan hobi yang dilakukan di luar rumah","answers":[{"answer":"olahraga","score":30},{"answer":"jalan-jalan","score":25},{"answer":"bersepeda","score":20},{"answer":"memancing","score":15},{"answer":"fotografi","score":10}]},
{"category":"Hobi & Hiburan","difficulty":"easy","question":"Sebutkan jenis film yang populer","answers":[{"answer":"action","score":30},{"answer":"komedi","score":25},{"answer":"horor","score":20},{"answer":"romantis","score":15},{"answer":"animasi","score":10}]},
{"category":"Hobi & Hiburan","difficulty":"easy","question":"Sebutkan aktivitas saat hujan","answers":[{"answer":"tidur","score":30},{"answer":"nonton","score":25},{"answer":"main game","score":20},{"answer":"makan","score":15},{"answer":"minum kopi","score":10}]},
{"category":"Hobi & Hiburan","difficulty":"easy","question":"Sebutkan alat untuk bermain game","answers":[{"answer":"hp","score":30},{"answer":"pc","score":25},{"answer":"console","score":20},{"answer":"laptop","score":15},{"answer":"tablet","score":10}]},
{"category":"Hobi & Hiburan","difficulty":"easy","question":"Sebutkan aktivitas di malam hari","answers":[{"answer":"tidur","score":30},{"answer":"nonton","score":25},{"answer":"main game","score":20},{"answer":"scroll hp","score":15},{"answer":"chat","score":10}]},
{"category":"Hobi & Hiburan","difficulty":"easy","question":"Sebutkan jenis olahraga santai","answers":[{"answer":"jalan kaki","score":30},{"answer":"jogging","score":25},{"answer":"bersepeda","score":20},{"answer":"yoga","score":15},{"answer":"renang","score":10}]},
{"category":"Hobi & Hiburan","difficulty":"easy","question":"Sebutkan aktivitas di pagi hari","answers":[{"answer":"sarapan","score":30},{"answer":"olahraga","score":25},{"answer":"mandi","score":20},{"answer":"jalan pagi","score":15},{"answer":"minum kopi","score":10}]},
{"category":"Hobi & Hiburan","difficulty":"easy","question":"Sebutkan aktivitas saat di perjalanan","answers":[{"answer":"denger musik","score":30},{"answer":"main hp","score":25},{"answer":"tidur","score":20},{"answer":"ngobrol","score":15},{"answer":"nonton","score":10}]},
{"category":"Hobi & Hiburan","difficulty":"easy","question":"Sebutkan jenis tontonan di TV","answers":[{"answer":"sinetron","score":30},{"answer":"berita","score":25},{"answer":"kartun","score":20},{"answer":"reality show","score":15},{"answer":"film","score":10}]},
{"category":"Hobi & Hiburan","difficulty":"easy","question":"Sebutkan aktivitas di rumah saat sendirian","answers":[{"answer":"tidur","score":30},{"answer":"nonton","score":25},{"answer":"main game","score":20},{"answer":"makan","score":15},{"answer":"denger musik","score":10}]},
{"category":"Hobi & Hiburan","difficulty":"easy","question":"Sebutkan aktivitas di media sosial","answers":[{"answer":"scroll","score":30},{"answer":"like","score":25},{"answer":"komen","score":20},{"answer":"post","score":15},{"answer":"share","score":10}]},
{"category":"Hobi & Hiburan","difficulty":"easy","question":"Sebutkan aktivitas yang bikin ketawa","answers":[{"answer":"nonton lucu","score":30},{"answer":"nongkrong","score":25},{"answer":"main game","score":20},{"answer":"ngobrol","score":15},{"answer":"lihat meme","score":10}]},
{"category":"Hobi & Hiburan","difficulty":"easy","question":"Sebutkan kegiatan di sekolah saat istirahat","answers":[{"answer":"jajan","score":30},{"answer":"ngobrol","score":25},{"answer":"main","score":20},{"answer":"tidur","score":15},{"answer":"main hp","score":10}]},
{"category":"Hobi & Hiburan","difficulty":"easy","question":"Sebutkan aktivitas saat nongkrong","answers":[{"answer":"ngobrol","score":30},{"answer":"makan","score":25},{"answer":"minum","score":20},{"answer":"main hp","score":15},{"answer":"ketawa","score":10}]},
{"category":"Hobi & Hiburan","difficulty":"easy","question":"Sebutkan aktivitas saat di kafe","answers":[{"answer":"ngobrol","score":30},{"answer":"minum kopi","score":25},{"answer":"foto","score":20},{"answer":"main hp","score":15},{"answer":"nugas","score":10}]},
{"category":"Hobi & Hiburan","difficulty":"easy","question":"Sebutkan aktivitas saat di bioskop","answers":[{"answer":"nonton","score":40},{"answer":"makan popcorn","score":25},{"answer":"minum","score":15},{"answer":"ngobrol","score":10},{"answer":"main hp","score":10}]},
{"category":"Hobi & Hiburan","difficulty":"easy","question":"Sebutkan aktivitas saat libur sekolah","answers":[{"answer":"main","score":30},{"answer":"tidur","score":25},{"answer":"jalan-jalan","score":20},{"answer":"main game","score":15},{"answer":"nonton","score":10}]},
{"category":"Hobi & Hiburan","difficulty":"easy","question":"Sebutkan kegiatan yang dilakukan di kamar","answers":[{"answer":"tidur","score":30},{"answer":"main hp","score":25},{"answer":"nonton","score":20},{"answer":"denger musik","score":15},{"answer":"main game","score":10}]},
{"category":"Hobi & Hiburan","difficulty":"easy","question":"Sebutkan aktivitas saat santai","answers":[{"answer":"tidur","score":30},{"answer":"nonton","score":25},{"answer":"denger musik","score":20},{"answer":"main hp","score":15},{"answer":"makan","score":10}]},
{"category":"Hobi & Hiburan","difficulty":"easy","question":"Sebutkan aktivitas untuk menghilangkan stres","answers":[{"answer":"tidur","score":30},{"answer":"jalan-jalan","score":25},{"answer":"nonton","score":20},{"answer":"main game","score":15},{"answer":"denger musik","score":10}]},
{"category":"Hobi & Hiburan","difficulty":"hard","question":"Sebutkan genre game yang butuh strategi tinggi","answers":[{"answer":"strategy","score":30},{"answer":"rts","score":25},{"answer":"turn based","score":20},{"answer":"simulation","score":15},{"answer":"card game","score":10}]},
{"category":"Hobi & Hiburan","difficulty":"hard","question":"Sebutkan kegiatan hiburan yang menghasilkan uang","answers":[{"answer":"streaming","score":30},{"answer":"youtuber","score":25},{"answer":"esport","score":20},{"answer":"content creator","score":15},{"answer":"musisi","score":10}]},
{"category":"Hobi & Hiburan","difficulty":"hard","question":"Sebutkan aktivitas yang butuh kreativitas tinggi","answers":[{"answer":"melukis","score":30},{"answer":"menulis","score":25},{"answer":"editing video","score":20},{"answer":"desain grafis","score":15},{"answer":"fotografi","score":10}]},
{"category":"Hobi & Hiburan","difficulty":"hard","question":"Sebutkan jenis hiburan yang butuh alat khusus","answers":[{"answer":"fotografi","score":30},{"answer":"musik","score":25},{"answer":"gaming","score":20},{"answer":"melukis","score":15},{"answer":"drone","score":10}]},
{"category":"Hobi & Hiburan","difficulty":"hard","question":"Sebutkan kegiatan yang biasa dilakukan sendirian","answers":[{"answer":"nonton","score":30},{"answer":"main game","score":25},{"answer":"membaca","score":20},{"answer":"denger musik","score":15},{"answer":"tidur","score":10}]},
{"category":"Hobi & Hiburan","difficulty":"hard","question":"Sebutkan aktivitas hiburan yang butuh internet","answers":[{"answer":"streaming","score":30},{"answer":"main game online","score":25},{"answer":"scroll sosmed","score":20},{"answer":"youtube","score":15},{"answer":"chat","score":10}]},
{"category":"Hobi & Hiburan","difficulty":"hard","question":"Sebutkan jenis konten hiburan di internet","answers":[{"answer":"vlog","score":30},{"answer":"gaming","score":25},{"answer":"tutorial","score":20},{"answer":"review","score":15},{"answer":"prank","score":10}]},
{"category":"Hobi & Hiburan","difficulty":"hard","question":"Sebutkan kegiatan hiburan yang bikin ketagihan","answers":[{"answer":"main game","score":30},{"answer":"scroll sosmed","score":25},{"answer":"nonton series","score":20},{"answer":"tiktok","score":15},{"answer":"youtube","score":10}]},
{"category":"Hobi & Hiburan","difficulty":"hard","question":"Sebutkan aktivitas hiburan yang mahal","answers":[{"answer":"traveling","score":30},{"answer":"koleksi barang","score":25},{"answer":"fotografi","score":20},{"answer":"gaming","score":15},{"answer":"konser","score":10}]},
{"category":"Hobi & Hiburan","difficulty":"hard","question":"Sebutkan aktivitas hiburan yang butuh skill","answers":[{"answer":"main musik","score":30},{"answer":"melukis","score":25},{"answer":"editing","score":20},{"answer":"gaming","score":15},{"answer":"menulis","score":10}]},
{"category":"Hobi & Hiburan","difficulty":"hard","question":"Sebutkan kegiatan hiburan di luar ruangan yang populer","answers":[{"answer":"camping","score":30},{"answer":"hiking","score":25},{"answer":"bersepeda","score":20},{"answer":"futsal","score":15},{"answer":"memancing","score":10}]},
{"category":"Hobi & Hiburan","difficulty":"hard","question":"Sebutkan jenis hiburan yang bersifat kompetitif","answers":[{"answer":"esport","score":30},{"answer":"olahraga","score":25},{"answer":"game online","score":20},{"answer":"lomba","score":15},{"answer":"turnamen","score":10}]},
{"category":"Hobi & Hiburan","difficulty":"hard","question":"Sebutkan aktivitas hiburan yang dilakukan saat sendirian di kamar","answers":[{"answer":"main hp","score":30},{"answer":"nonton","score":25},{"answer":"main game","score":20},{"answer":"denger musik","score":15},{"answer":"tidur","score":10}]},
{"category":"Hobi & Hiburan","difficulty":"hard","question":"Sebutkan jenis hiburan yang populer di kalangan remaja","answers":[{"answer":"tiktok","score":30},{"answer":"game online","score":25},{"answer":"nongkrong","score":20},{"answer":"youtube","score":15},{"answer":"instagram","score":10}]},
{"category":"Hobi & Hiburan","difficulty":"hard","question":"Sebutkan aktivitas hiburan saat perjalanan jauh","answers":[{"answer":"denger musik","score":30},{"answer":"tidur","score":25},{"answer":"main hp","score":20},{"answer":"nonton","score":15},{"answer":"ngobrol","score":10}]},
{"category":"Hobi & Hiburan","difficulty":"hard","question":"Sebutkan kegiatan hiburan yang bisa dilakukan tanpa alat","answers":[{"answer":"ngobrol","score":30},{"answer":"jalan-jalan","score":25},{"answer":"tidur","score":20},{"answer":"melamun","score":15},{"answer":"bernyanyi","score":10}]},
{"category":"Hobi & Hiburan","difficulty":"hard","question":"Sebutkan jenis hiburan yang bisa dilakukan bersama banyak orang","answers":[{"answer":"game","score":30},{"answer":"nongkrong","score":25},{"answer":"olahraga","score":20},{"answer":"konser","score":15},{"answer":"party","score":10}]},
{"category":"Hobi & Hiburan","difficulty":"hard","question":"Sebutkan aktivitas hiburan yang berhubungan dengan teknologi","answers":[{"answer":"gaming","score":30},{"answer":"streaming","score":25},{"answer":"editing","score":20},{"answer":"coding","score":15},{"answer":"vr","score":10}]},
{"category":"Hobi & Hiburan","difficulty":"hard","question":"Sebutkan kegiatan hiburan yang dilakukan di malam hari","answers":[{"answer":"nonton","score":30},{"answer":"main game","score":25},{"answer":"nongkrong","score":20},{"answer":"denger musik","score":15},{"answer":"scroll hp","score":10}]},
{"category":"Hobi & Hiburan","difficulty":"hard","question":"Sebutkan aktivitas hiburan yang sering dilakukan saat gabut","answers":[{"answer":"scroll sosmed","score":30},{"answer":"main game","score":25},{"answer":"nonton","score":20},{"answer":"tidur","score":15},{"answer":"denger musik","score":10}]},
{"category":"Hobi & Hiburan","difficulty":"hard","question":"Sebutkan profesi di dunia hiburan digital","answers":[{"answer":"streamer","score":30},{"answer":"youtuber","score":25},{"answer":"vtuber","score":20},{"answer":"content creator","score":15},{"answer":"influencer","score":10}]},
{"category":"Hobi & Hiburan","difficulty":"hard","question":"Sebutkan jenis editing dalam dunia konten","answers":[{"answer":"video editing","score":30},{"answer":"photo editing","score":25},{"answer":"color grading","score":20},{"answer":"sound editing","score":15},{"answer":"motion graphic","score":10}]},
{"category":"Hobi & Hiburan","difficulty":"hard","question":"Sebutkan platform live streaming","answers":[{"answer":"twitch","score":30},{"answer":"youtube live","score":25},{"answer":"facebook live","score":20},{"answer":"tiktok live","score":15},{"answer":"nimo tv","score":10}]},
{"category":"Hobi & Hiburan","difficulty":"hard","question":"Sebutkan aktivitas dalam produksi video","answers":[{"answer":"shooting","score":30},{"answer":"editing","score":25},{"answer":"script writing","score":20},{"answer":"directing","score":15},{"answer":"rendering","score":10}]},
{"category":"Hobi & Hiburan","difficulty":"hard","question":"Sebutkan peralatan untuk content creator","answers":[{"answer":"kamera","score":30},{"answer":"mic","score":25},{"answer":"lighting","score":20},{"answer":"tripod","score":15},{"answer":"pc","score":10}]},
{"category":"Hobi & Hiburan","difficulty":"hard","question":"Sebutkan istilah dalam dunia gaming kompetitif","answers":[{"answer":"rank","score":30},{"answer":"mmr","score":25},{"answer":"scrim","score":20},{"answer":"meta","score":15},{"answer":"nerf","score":10}]},
{"category":"Hobi & Hiburan","difficulty":"hard","question":"Sebutkan jenis konten yang butuh scripting","answers":[{"answer":"film pendek","score":30},{"answer":"sketsa","score":25},{"answer":"drama","score":20},{"answer":"iklan","score":15},{"answer":"youtube skit","score":10}]},
{"category":"Hobi & Hiburan","difficulty":"hard","question":"Sebutkan aktivitas dalam dunia musik digital","answers":[{"answer":"mixing","score":30},{"answer":"mastering","score":25},{"answer":"recording","score":20},{"answer":"composing","score":15},{"answer":"arranging","score":10}]},
{"category":"Hobi & Hiburan","difficulty":"hard","question":"Sebutkan jenis file dalam dunia hiburan digital","answers":[{"answer":"mp4","score":30},{"answer":"mp3","score":25},{"answer":"jpg","score":20},{"answer":"png","score":15},{"answer":"wav","score":10}]},
{"category":"Hobi & Hiburan","difficulty":"hard","question":"Sebutkan aktivitas di balik layar produksi hiburan","answers":[{"answer":"editing","score":30},{"answer":"lighting setup","score":25},{"answer":"sound check","score":20},{"answer":"script","score":15},{"answer":"camera setup","score":10}]},
  {"category":"Hobi & Hiburan","subcategory":"Game","difficulty":"easy","question":"Sebutkan karakter game terkenal","answers":[{"answer":"mario","score":30},{"answer":"sonic","score":25},{"answer":"link","score":20},{"answer":"kratos","score":15},{"answer":"lara croft","score":10}]},
  {"category":"Hobi & Hiburan","subcategory":"Game","difficulty":"easy","question":"Yang termasuk genre game populer","answers":[{"answer":"rpg","score":30},{"answer":"fps","score":25},{"answer":"moba","score":20},{"answer":"battle royale","score":15},{"answer":"racing","score":10}]},
  {"category":"Hobi & Hiburan","subcategory":"Game","difficulty":"easy","question":"Sebutkan game mobile terkenal","answers":[{"answer":"ml","score":30},{"answer":"pubg","score":25},{"answer":"coc","score":20},{"answer":"free fire","score":15},{"answer":"genshin","score":10}]},
  {"category":"Hobi & Hiburan","subcategory":"Game","difficulty":"easy","question":"Yang termasuk konsol game","answers":[{"answer":"ps","score":30},{"answer":"xbox","score":25},{"answer":"switch","score":20},{"answer":"wii","score":15},{"answer":"psp","score":10}]},
  {"category":"Hobi & Hiburan","subcategory":"Game","difficulty":"easy","question":"Sebutkan game balapan","answers":[{"answer":"nfs","score":30},{"answer":"forza","score":25},{"answer":"gt","score":20},{"answer":"asphalt","score":15},{"answer":"mario kart","score":10}]},
  {"category":"Hobi & Hiburan","subcategory":"Game","difficulty":"easy","question":"Game yang ada zombie","answers":[{"answer":"re","score":30},{"answer":"l4d","score":25},{"answer":"days gone","score":20},{"answer":"dying light","score":15},{"answer":"codzombie","score":10}]},
  {"category":"Hobi & Hiburan","subcategory":"Game","difficulty":"easy","question":"Sebutkan karakter mario","answers":[{"answer":"luigi","score":30},{"answer":"peach","score":25},{"answer":"bowser","score":20},{"answer":"yoshi","score":15},{"answer":"toad","score":10}]},
  {"category":"Hobi & Hiburan","subcategory":"Game","difficulty":"easy","question":"Yang termasuk game battle royale","answers":[{"answer":"pubg","score":30},{"answer":"fortnite","score":25},{"answer":"apex","score":20},{"answer":"ff","score":15},{"answer":"warzone","score":10}]},
  {"category":"Hobi & Hiburan","subcategory":"Game","difficulty":"easy","question":"Sebutkan game bola","answers":[{"answer":"fifa","score":30},{"answer":"pes","score":25},{"answer":"fm","score":20},{"answer":"efootball","score":15},{"answer":"rocket league","score":10}]},
  {"category":"Hobi & Hiburan","subcategory":"Game","difficulty":"easy","question":"Yang termasuk game horror","answers":[{"answer":"outlast","score":30},{"answer":"amnesia","score":25},{"answer":"re","score":20},{"answer":"silent hill","score":15},{"answer":"phasmophobia","score":10}]},
  {"category":"Hobi & Hiburan","subcategory":"Game","difficulty":"easy","question":"Sebutkan karakter pokemon","answers":[{"answer":"pikachu","score":30},{"answer":"charizard","score":25},{"answer":"bulbasaur","score":20},{"answer":"squirtle","score":15},{"answer":"eevee","score":10}]},
  {"category":"Hobi & Hiburan","subcategory":"Game","difficulty":"easy","question":"Yang termasuk game offline","answers":[{"answer":"gta","score":30},{"answer":"skyrim","score":25},{"answer":"witcher","score":20},{"answer":"god of war","score":15},{"answer":"rdr","score":10}]},
  {"category":"Hobi & Hiburan","subcategory":"Game","difficulty":"easy","question":"Sebutkan game fps terkenal","answers":[{"answer":"cod","score":30},{"answer":"cs","score":25},{"answer":"valorant","score":20},{"answer":"battlefield","score":15},{"answer":"halo","score":10}]},
  {"category":"Hobi & Hiburan","subcategory":"Game","difficulty":"easy","question":"Yang termasuk item di game","answers":[{"answer":"potion","score":30},{"answer":"sword","score":25},{"answer":"shield","score":20},{"answer":"armor","score":15},{"answer":"gold","score":10}]},
  {"category":"Hobi & Hiburan","subcategory":"Game","difficulty":"easy","question":"Sebutkan game open world","answers":[{"answer":"gta","score":30},{"answer":"minecraft","score":25},{"answer":"rdr","score":20},{"answer":"zelda","score":15},{"answer":"skyrim","score":10}]},
  {"category":"Hobi & Hiburan","subcategory":"Game","difficulty":"easy","question":"Yang termasuk game sandbox","answers":[{"answer":"minecraft","score":30},{"answer":"terraria","score":25},{"answer":"roblox","score":20},{"answer":"gmod","score":15},{"answer":"sims","score":10}]},
  {"category":"Hobi & Hiburan","subcategory":"Game","difficulty":"easy","question":"Sebutkan karakter tekken","answers":[{"answer":"jin","score":30},{"answer":"kazuya","score":25},{"answer":"paul","score":20},{"answer":"law","score":15},{"answer":"king","score":10}]},
  {"category":"Hobi & Hiburan","subcategory":"Game","difficulty":"easy","question":"Yang termasuk game strategi","answers":[{"answer":"coc","score":30},{"answer":"aoe","score":25},{"answer":"civ","score":20},{"answer":"sc","score":15},{"answer":"total war","score":10}]},
  {"category":"Hobi & Hiburan","subcategory":"Game","difficulty":"easy","question":"Sebutkan karakter ml","answers":[{"answer":"layla","score":30},{"answer":"miya","score":25},{"answer":"zilong","score":20},{"answer":"alucard","score":15},{"answer":"saber","score":10}]},
  {"category":"Hobi & Hiburan","subcategory":"Game","difficulty":"easy","question":"Yang termasuk game co-op","answers":[{"answer":"it takes two","score":30},{"answer":"a way out","score":25},{"answer":"l4d","score":20},{"answer":"overcooked","score":15},{"answer":"phasmophobia","score":10}]},
  {"category":"Hobi & Hiburan","subcategory":"Game","difficulty":"hard","question":"Sebutkan karakter di gta","answers":[{"answer":"cj","score":30},{"answer":"tommy","score":25},{"answer":"nico","score":20},{"answer":"trevor","score":15},{"answer":"michael","score":10}]},
  {"category":"Hobi & Hiburan","subcategory":"Game","difficulty":"hard","question":"Yang termasuk game soulslike","answers":[{"answer":"darksouls","score":30},{"answer":"elden ring","score":25},{"answer":"bloodborne","score":20},{"answer":"sekiro","score":15},{"answer":"nioh","score":10}]},
  {"category":"Hobi & Hiburan","subcategory":"Game","difficulty":"hard","question":"Sebutkan hero dota","answers":[{"answer":"invoker","score":30},{"answer":"pudge","score":25},{"answer":"juggernaut","score":20},{"answer":"axe","score":15},{"answer":"sf","score":10}]},
  {"category":"Hobi & Hiburan","subcategory":"Game","difficulty":"hard","question":"Yang termasuk developer game","answers":[{"answer":"ea","score":30},{"answer":"ubisoft","score":25},{"answer":"rockstar","score":20},{"answer":"capcom","score":15},{"answer":"nintendo","score":10}]},
  {"category":"Hobi & Hiburan","subcategory":"Game","difficulty":"hard","question":"Sebutkan karakter di tekken","answers":[{"answer":"jin","score":30},{"answer":"kazuya","score":25},{"answer":"heihachi","score":20},{"answer":"paul","score":15},{"answer":"law","score":10}]},
  {"category":"Hobi & Hiburan","subcategory":"Game","difficulty":"hard","question":"Yang termasuk boss di game","answers":[{"answer":"bowser","score":30},{"answer":"ganon","score":25},{"answer":"sephiroth","score":20},{"answer":"vergil","score":15},{"answer":"arthas","score":10}]},
  {"category":"Hobi & Hiburan","subcategory":"Game","difficulty":"hard","question":"Sebutkan karakter ff","answers":[{"answer":"cloud","score":30},{"answer":"sephiroth","score":25},{"answer":"tifa","score":20},{"answer":"aerith","score":15},{"answer":"squall","score":10}]},
  {"category":"Hobi & Hiburan","subcategory":"Game","difficulty":"hard","question":"Yang termasuk game indie terkenal","answers":[{"answer":"undertale","score":30},{"answer":"hades","score":25},{"answer":"celeste","score":20},{"answer":"stardew","score":15},{"answer":"hollow knight","score":10}]},
  {"category":"Hobi & Hiburan","subcategory":"Game","difficulty":"hard","question":"Sebutkan karakter resident evil","answers":[{"answer":"leon","score":30},{"answer":"chris","score":25},{"answer":"jill","score":20},{"answer":"ada","score":15},{"answer":"claire","score":10}]},
  {"category":"Hobi & Hiburan","subcategory":"Game","difficulty":"hard","question":"Yang termasuk senjata di fps","answers":[{"answer":"ak47","score":30},{"answer":"m4","score":25},{"answer":"awp","score":20},{"answer":"scar","score":15},{"answer":"uzi","score":10}]},
  {"category":"Hobi & Hiburan","subcategory":"Game","difficulty":"hard","question":"Sebutkan karakter mortal kombat","answers":[{"answer":"scorpion","score":30},{"answer":"subzero","score":25},{"answer":"raiden","score":20},{"answer":"liu kang","score":15},{"answer":"kitana","score":10}]},
  {"category":"Hobi & Hiburan","subcategory":"Game","difficulty":"hard","question":"Yang termasuk map di game fps","answers":[{"answer":"dust2","score":30},{"answer":"mirage","score":25},{"answer":"inferno","score":20},{"answer":"nuketown","score":15},{"answer":"erangel","score":10}]},
  {"category":"Hobi & Hiburan","subcategory":"Game","difficulty":"hard","question":"Sebutkan karakter overwatch","answers":[{"answer":"tracer","score":30},{"answer":"genji","score":25},{"answer":"mercy","score":20},{"answer":"reaper","score":15},{"answer":"hanzo","score":10}]},
  {"category":"Hobi & Hiburan","subcategory":"Game","difficulty":"hard","question":"Yang termasuk game stealth","answers":[{"answer":"mgs","score":30},{"answer":"hitman","score":25},{"answer":"splinter cell","score":20},{"answer":"thief","score":15},{"answer":"dishonored","score":10}]},
  {"category":"Hobi & Hiburan","subcategory":"Game","difficulty":"hard","question":"Sebutkan karakter zelda","answers":[{"answer":"link","score":30},{"answer":"zelda","score":25},{"answer":"ganon","score":20},{"answer":"impa","score":15},{"answer":"midna","score":10}]},
  {"category":"Hobi & Hiburan","subcategory":"Game","difficulty":"hard","question":"Yang termasuk game survival","answers":[{"answer":"rust","score":30},{"answer":"ark","score":25},{"answer":"forest","score":20},{"answer":"dayz","score":15},{"answer":"raft","score":10}]},
  {"category":"Hobi & Hiburan","subcategory":"Game","difficulty":"hard","question":"Sebutkan karakter street fighter","answers":[{"answer":"ryu","score":30},{"answer":"ken","score":25},{"answer":"chunli","score":20},{"answer":"guile","score":15},{"answer":"bison","score":10}]},
  {"category":"Hobi & Hiburan","subcategory":"Game","difficulty":"hard","question":"Yang termasuk item rare di game","answers":[{"answer":"legendary","score":30},{"answer":"epic","score":25},{"answer":"mythic","score":20},{"answer":"ultra rare","score":15},{"answer":"exotic","score":10}]},
  {"category":"Hobi & Hiburan","subcategory":"Game","difficulty":"hard","question":"Sebutkan karakter genshin","answers":[{"answer":"diluc","score":30},{"answer":"keqing","score":25},{"answer":"venti","score":20},{"answer":"zhongli","score":15},{"answer":"raiden","score":10}]},
  {"category":"Hobi & Hiburan","subcategory":"Game","difficulty":"hard","question":"Yang termasuk mode game","answers":[{"answer":"ranked","score":30},{"answer":"casual","score":25},{"answer":"arcade","score":20},{"answer":"story","score":15},{"answer":"survival","score":10}]}
]